suits/__init__.py
suits/donna.py
suits-0.0.2.dist-info/METADATA
suits-0.0.2.dist-info/WHEEL
suits-0.0.2.dist-info/top_level.txt
suits-0.0.2.dist-info/RECORD
