Metadata-Version: 2.1
Name: suits
Version: 0.0.2
Summary: Ask Donna to do things for you, instead of worrying about pesky syntactical mumbo-jumbo. NOT intended for production purposes.
Author: Ishan Sandeep Kshirsagar
Author-email: ishank20062002@gmail.com
Requires-Dist: google-generativeai
Requires-Dist: shutup
